fastsaverclient/__init__.py
fastsaverclient/client.py
fastsaverclient-0.1.0.dist-info/METADATA
fastsaverclient-0.1.0.dist-info/WHEEL
fastsaverclient-0.1.0.dist-info/top_level.txt
fastsaverclient-0.1.0.dist-info/RECORD
