Metadata-Version: 2.2
Name: fastsaverclient
Version: 0.1.0
Summary: FastSaver API Client
Home-page: https://github.com/coder2077/fastsaverclient
Author: coder2077
Author-email: abdullatif.developer@gmail.com
Classifier: Programming Language :: Python :: 3
Classifier: License :: OSI Approved :: MIT License
Classifier: Operating System :: OS Independent
Requires-Python: >=3.7
Requires-Dist: aiofiles==24.1.0
Requires-Dist: anyio==4.8.0
Requires-Dist: certifi==2024.12.14
Requires-Dist: h11==0.14.0
Requires-Dist: httpcore==1.0.7
Requires-Dist: httpx==0.28.1
Requires-Dist: idna==3.10
Requires-Dist: setuptools==75.8.0
Requires-Dist: shortuuid==1.0.13
Requires-Dist: sniffio==1.3.1
Dynamic: author
Dynamic: author-email
Dynamic: classifier
Dynamic: home-page
Dynamic: requires-dist
Dynamic: requires-python
Dynamic: summary
